ammaritproj/Triangle.py
ammaritproj/__init__.py
ammaproj-0.1.1.dist-info/METADATA
ammaproj-0.1.1.dist-info/WHEEL
ammaproj-0.1.1.dist-info/top_level.txt
ammaproj-0.1.1.dist-info/RECORD
