Metadata-Version: 2.4
Name: ammaproj
Version: 0.1.1
Summary: This is my first package . A simple example package to discribes Triangle.
Home-page: https://github.com/Amarit1008/AmaritPg
Author: N. Amarittabut
Author-email: nabeel65010@email.com
Requires-Python: >=3.8
Dynamic: author
Dynamic: author-email
Dynamic: description
Dynamic: description-content-type
Dynamic: home-page
Dynamic: requires-python
Dynamic: summary
